COPYING
wechat_backup/__init__.py
wechat_backup/__main__.py
wechat_backup/commands/__init__.py
wechat_backup/commands/extract_contacts.py
wechat_backup/commands/extract_messages.py
wechat_backup/contact.py
wechat_backup/context.py
wechat_backup/helper.py
wechat_backup/message/__init__.py
wechat_backup/message/parser.py
wechat_backup/message/typing.py
wechat_backup/platform/__init__.py
wechat_backup/platform/android/__init__.py
wechat_backup/platform/android/contact.py
wechat_backup/platform/android/context.py
wechat_backup/platform/android/message.py
wechat_backup/platform/ios/__init__.py
wechat_backup/platform/ios/contact.py
wechat_backup/platform/ios/context.py
wechat_backup/platform/ios/message.py
wechat_backup-2.1.0.dist-info/COPYING
wechat_backup-2.1.0.dist-info/METADATA
wechat_backup-2.1.0.dist-info/WHEEL
wechat_backup-2.1.0.dist-info/entry_points.txt
wechat_backup-2.1.0.dist-info/RECORD
